README
setup.py
scramble/__init__.py
scramble/server.py
scrambled.egg-info/PKG-INFO
scrambled.egg-info/SOURCES.txt
scrambled.egg-info/dependency_links.txt
scrambled.egg-info/entry_points.txt
scrambled.egg-info/top_level.txt