Metadata-Version: 1.0
Name: scrambled
Version: 0.2
Summary: a PyPI-compatible package server
Home-page: http://code.google.com/p/scrambled
Author: Brandon Gilmore
Author-email: brandon@mg2.org
License: BSD
Platform: any
